{"frames": [

{
	"filename": "frame1.png",
	"frame": {"x":318,"y":1,"w":205,"h":228},
	"rotated": false,
	"trimmed": true,
	"spriteSourceSize": {"x":5,"y":22,"w":205,"h":228},
	"sourceSize": {"w":247,"h":259}
},
{
	"filename": "frame2.png",
	"frame": {"x":1055,"y":1,"w":173,"h":209},
	"rotated": false,
	"trimmed": true,
	"spriteSourceSize": {"x":9,"y":35,"w":173,"h":209},
	"sourceSize": {"w":247,"h":259}
},
{
	"filename": "frame3.png",
	"frame": {"x":723,"y":1,"w":137,"h":224},
	"rotated": false,
	"trimmed": true,
	"spriteSourceSize": {"x":14,"y":25,"w":137,"h":224},
	"sourceSize": {"w":247,"h":259}
},
{
	"filename": "frame4.png",
	"frame": {"x":172,"y":1,"w":144,"h":229},
	"rotated": false,
	"trimmed": true,
	"spriteSourceSize": {"x":13,"y":21,"w":144,"h":229},
	"sourceSize": {"w":247,"h":259}
},
{
	"filename": "frame5.png",
	"frame": {"x":1,"y":1,"w":169,"h":233},
	"rotated": false,
	"trimmed": true,
	"spriteSourceSize": {"x":10,"y":19,"w":169,"h":233},
	"sourceSize": {"w":247,"h":259}
},
{
	"filename": "frame6.png",
	"frame": {"x":862,"y":1,"w":191,"h":216},
	"rotated": false,
	"trimmed": true,
	"spriteSourceSize": {"x":7,"y":30,"w":191,"h":216},
	"sourceSize": {"w":247,"h":259}
},
{
	"filename": "frame7.png",
	"frame": {"x":525,"y":1,"w":196,"h":227},
	"rotated": false,
	"trimmed": true,
	"spriteSourceSize": {"x":6,"y":23,"w":196,"h":227},
	"sourceSize": {"w":247,"h":259}
}],
"meta": {
	"app": "https://www.codeandweb.com/texturepacker",
	"version": "1.0",
	"image": "running_spritesheet.png",
	"format": "RGBA8888",
	"size": {"w":1229,"h":235},
	"scale": "1",
	"smartupdate": "$TexturePacker:SmartUpdate:67e0b81951fd8f7a79e80a6abcbb3bd0:b6d2d5eb00f23a80784798e9a053f6b6:b6b3a86ab8a919ee99490e78df6a1d24$"
}
}
